README.md
__init__.py
jwt.py
immersa_jwt.egg-info/PKG-INFO
immersa_jwt.egg-info/SOURCES.txt
immersa_jwt.egg-info/dependency_links.txt
immersa_jwt.egg-info/requires.txt
immersa_jwt.egg-info/top_level.txt
immersa_jwt-1.0.0.dist-info/METADATA
immersa_jwt-1.0.0.dist-info/WHEEL
immersa_jwt-1.0.0.dist-info/top_level.txt
immersa_jwt-1.0.0.dist-info/RECORD
