Metadata-Version: 2.1
Name: immersa-jwt
Version: 1.0.0
Summary: A library Generate JWT, validate, and extract session info from JWT
Home-page: https://github.com/immersa-co/jwt
Author: Prisdha Dharma
Author-email: prisdha@immersa.co
License: MIT
Platform: UNKNOWN
Classifier: License :: OSI Approved :: MIT License
Classifier: Programming Language :: Python :: 3
Classifier: Programming Language :: Python :: 3.7
Requires-Dist: python-jose
